{
  "exams": [
    {
      "id": "1",
      "name": "AWS SOLUTION ARCH",
      "course": "Math 101",
      "description": "Covers algebra, calculus and geometry",
      "date": "2025-05-10",
      "start_time": "2025-05-10T09:00:00",
      "end_time": "2025-05-10T11:00:00",
      "duration": 120,
      "status": "upcoming",
      "is_published": true,
      "is_expired": false,
      "show_results_immediately": true,
      "shuffle_questions": true,
      "shuffle_options": true,
      "pass_percentage": 50,
      "total_marks": 100,
      "created_at": "2025-04-20T10:00:00",
      "updated_at": "2025-04-20T10:00:00",
      "totalQuestions": 30,
      "qualifyingMark": null
    },
    {
      "id": "2",
      "name": "Physics Midterm",
      "course": "Physics 102",
      "description": "Mechanics and thermodynamics",
      "date": "2025-04-25",
      "start_time": "2025-04-25T13:00:00",
      "end_time": "2025-04-25T14:30:00",
      "duration": 90,
      "status": "active",
      "is_published": true,
      "is_expired": false,
      "show_results_immediately": false,
      "shuffle_questions": false,
      "shuffle_options": true,
      "pass_percentage": 60,
      "total_marks": 75,
      "created_at": "2025-04-15T09:30:00",
      "updated_at": "2025-04-21T15:00:00",
      "totalQuestions": 30,
      "qualifyingMark": null
    },
    {
      "id": "3",
      "name": "Chemistry Unit Test",
      "course": "Chem 103",
      "description": "Organic and inorganic chemistry",
      "date": "2025-04-22",
      "start_time": "2025-04-22T10:00:00",
      "end_time": "2025-04-22T11:00:00",
      "duration": 60,
      "status": "completed",
      "is_published": true,
      "is_expired": true,
      "show_results_immediately": true,
      "shuffle_questions": true,
      "shuffle_options": false,
      "pass_percentage": 40,
      "total_marks": 50,
      "created_at": "2025-04-10T12:00:00",
      "updated_at": "2025-04-22T12:00:00",
      "totalQuestions": 30,
      "qualifyingMark": null
    },
    {
      "id": "4",
      "name": "English Literature Quiz",
      "course": "English 201",
      "description": "Shakespeare and modern poets",
      "date": "2025-05-05",
      "start_time": "2025-05-05T08:30:00",
      "end_time": "2025-05-05T09:30:00",
      "duration": 60,
      "status": "upcoming",
      "is_published": false,
      "is_expired": false,
      "show_results_immediately": false,
      "shuffle_questions": true,
      "shuffle_options": true,
      "pass_percentage": 55,
      "total_marks": 60,
      "created_at": "2025-04-21T10:00:00",
      "updated_at": "2025-04-21T10:00:00",
      "totalQuestions": 30,
      "qualifyingMark": null
    },
    {
      "id": "5",
      "name": "History Final",
      "course": "History 301",
      "description": "World wars and revolutions",
      "date": "2025-06-01",
      "start_time": "2025-06-01T12:00:00",
      "end_time": "2025-06-01T14:00:00",
      "duration": 120,
      "status": "upcoming",
      "is_published": false,
      "is_expired": false,
      "show_results_immediately": true,
      "shuffle_questions": false,
      "shuffle_options": false,
      "pass_percentage": 45,
      "total_marks": 80,
      "created_at": "2025-04-19T15:00:00",
      "updated_at": "2025-04-20T15:00:00",
      "totalQuestions": 30,
      "qualifyingMark": null
    },
    {
      "id": "6",
      "name": "Computer Science Lab Test",
      "course": "CS 210",
      "description": "C programming and debugging",
      "date": "2025-04-29",
      "start_time": "2025-04-29T14:00:00",
      "end_time": "2025-04-29T15:30:00",
      "duration": 90,
      "status": "active",
      "is_published": true,
      "is_expired": false,
      "show_results_immediately": true,
      "shuffle_questions": false,
      "shuffle_options": false,
      "pass_percentage": 50,
      "total_marks": 70,
      "created_at": "2025-04-18T11:30:00",
      "updated_at": "2025-04-21T12:00:00",
      "totalQuestions": 30,
      "qualifyingMark": null
    },
    {
      "id": "7",
      "name": "Economics Quiz",
      "course": "Econ 104",
      "description": "Microeconomics basics",
      "date": "2025-05-03",
      "start_time": "2025-05-03T10:00:00",
      "end_time": "2025-05-03T11:00:00",
      "duration": 60,
      "status": "upcoming",
      "is_published": true,
      "is_expired": false,
      "show_results_immediately": true,
      "shuffle_questions": true,
      "shuffle_options": false,
      "pass_percentage": 50,
      "total_marks": 40,
      "created_at": "2025-04-18T10:00:00",
      "updated_at": "2025-04-18T10:00:00",
      "totalQuestions": 30,
      "qualifyingMark": null
    },
    {
      "id": "8",
      "name": "Biology Practical",
      "course": "Bio 110",
      "description": "Lab and diagram-based questions",
      "date": "2025-04-28",
      "start_time": "2025-04-28T11:00:00",
      "end_time": "2025-04-28T12:30:00",
      "duration": 90,
      "status": "active",
      "is_published": false,
      "is_expired": false,
      "show_results_immediately": false,
      "shuffle_questions": true,
      "shuffle_options": true,
      "pass_percentage": 60,
      "total_marks": 60,
      "created_at": "2025-04-19T14:00:00",
      "updated_at": "2025-04-21T14:00:00",
      "totalQuestions": 30,
      "qualifyingMark": null
    },
    {
      "id": "9",
      "name": "Sociology Internal",
      "course": "Soc 202",
      "description": "Social theories and culture",
      "date": "2025-05-12",
      "start_time": "2025-05-12T09:00:00",
      "end_time": "2025-05-12T10:30:00",
      "duration": 90,
      "status": "upcoming",
      "is_published": true,
      "is_expired": false,
      "show_results_immediately": true,
      "shuffle_questions": false,
      "shuffle_options": false,
      "pass_percentage": 50,
      "total_marks": 60,
      "created_at": "2025-04-22T08:00:00",
      "updated_at": "2025-04-22T08:00:00",
      "totalQuestions": 30,
      "qualifyingMark": null
    },
    {
      "id": "11",
      "name": "Business Studies Test",
      "course": "BS 120",
      "description": "Marketing and management",
      "date": "2025-05-15",
      "start_time": "2025-05-15T10:00:00",
      "end_time": "2025-05-15T11:30:00",
      "duration": 90,
      "status": "upcoming",
      "is_published": true,
      "is_expired": false,
      "show_results_immediately": false,
      "shuffle_questions": false,
      "shuffle_options": false,
      "pass_percentage": 50,
      "total_marks": 80,
      "created_at": "2025-04-22T11:00:00",
      "updated_at": "2025-04-22T11:00:00",
      "totalQuestions": 30,
      "qualifyingMark": null
    },
    {
      "id": "12",
      "name": "Business Studies Test",
      "course": "BS 120",
      "description": "Marketing and management",
      "date": "2025-05-15",
      "start_time": "2025-05-15T10:00:00",
      "end_time": "2025-05-15T11:30:00",
      "duration": 90,
      "status": "upcoming",
      "is_published": true,
      "is_expired": false,
      "show_results_immediately": false,
      "shuffle_questions": false,
      "shuffle_options": false,
      "pass_percentage": 50,
      "total_marks": 80,
      "created_at": "2025-04-22T11:00:00",
      "updated_at": "2025-04-22T11:00:00",
      "totalQuestions": 30,
      "qualifyingMark": null
    },
    {
      "id": "13",
      "name": "Business Studies Test",
      "course": "BS 120",
      "description": "Marketing and management",
      "date": "2025-05-15",
      "start_time": "2025-05-15T10:00:00",
      "end_time": "2025-05-15T11:30:00",
      "duration": 90,
      "status": "upcoming",
      "is_published": true,
      "is_expired": false,
      "show_results_immediately": false,
      "shuffle_questions": false,
      "shuffle_options": false,
      "pass_percentage": 50,
      "total_marks": 80,
      "created_at": "2025-04-22T11:00:00",
      "updated_at": "2025-04-22T11:00:00",
      "totalQuestions": 30,
      "qualifyingMark": null
    },
    {
      "id": "14",
      "name": "Business Studies Test",
      "course": "BS 120",
      "description": "Marketing and management",
      "date": "2025-05-15",
      "start_time": "2025-05-15T10:00:00",
      "end_time": "2025-05-15T11:30:00",
      "duration": 90,
      "status": "upcoming",
      "is_published": true,
      "is_expired": false,
      "show_results_immediately": false,
      "shuffle_questions": false,
      "shuffle_options": false,
      "pass_percentage": 50,
      "total_marks": 80,
      "created_at": "2025-04-22T11:00:00",
      "updated_at": "2025-04-22T11:00:00",
      "totalQuestions": 30,
      "qualifyingMark": null
    },
    {
      "id": "15",
      "name": "Business Studies Test",
      "course": "BS 120",
      "description": "Marketing and management",
      "date": "2025-05-15",
      "start_time": "2025-05-15T10:00:00",
      "end_time": "2025-05-15T11:30:00",
      "duration": 90,
      "status": "upcoming",
      "is_published": true,
      "is_expired": false,
      "show_results_immediately": false,
      "shuffle_questions": false,
      "shuffle_options": false,
      "pass_percentage": 50,
      "total_marks": 80,
      "created_at": "2025-04-22T11:00:00",
      "updated_at": "2025-04-22T11:00:00",
      "totalQuestions": 30,
      "qualifyingMark": null
    },
    {
      "id": "16",
      "name": "Business Studies Test",
      "course": "BS 120",
      "description": "Marketing and management",
      "date": "2025-05-15",
      "start_time": "2025-05-15T10:00:00",
      "end_time": "2025-05-15T11:30:00",
      "duration": 90,
      "status": "upcoming",
      "is_published": true,
      "is_expired": false,
      "show_results_immediately": false,
      "shuffle_questions": false,
      "shuffle_options": false,
      "pass_percentage": 50,
      "total_marks": 80,
      "created_at": "2025-04-22T11:00:00",
      "updated_at": "2025-04-22T11:00:00",
      "totalQuestions": 30,
      "qualifyingMark": null
    },
    {
      "id": "17",
      "name": "Business Studies Test",
      "course": "BS 120",
      "description": "Marketing and management",
      "date": "2025-05-15",
      "start_time": "2025-05-15T10:00:00",
      "end_time": "2025-05-15T11:30:00",
      "duration": 90,
      "status": "upcoming",
      "is_published": true,
      "is_expired": false,
      "show_results_immediately": false,
      "shuffle_questions": false,
      "shuffle_options": false,
      "pass_percentage": 50,
      "total_marks": 80,
      "created_at": "2025-04-22T11:00:00",
      "updated_at": "2025-04-22T11:00:00",
      "totalQuestions": 30,
      "qualifyingMark": null
    },
    {
      "id": "18",
      "name": "Business Studies Test",
      "course": "BS 120",
      "description": "Marketing and management",
      "date": "2025-05-15",
      "start_time": "2025-05-15T10:00:00",
      "end_time": "2025-05-15T11:30:00",
      "duration": 90,
      "status": "upcoming",
      "is_published": true,
      "is_expired": false,
      "show_results_immediately": false,
      "shuffle_questions": false,
      "shuffle_options": false,
      "pass_percentage": 50,
      "total_marks": 80,
      "created_at": "2025-04-22T11:00:00",
      "updated_at": "2025-04-22T11:00:00",
      "totalQuestions": 30,
      "qualifyingMark": null
    },
    {
      "id": "19",
      "name": "Business Studies Test",
      "course": "BS 120",
      "description": "Marketing and management",
      "date": "2025-05-15",
      "start_time": "2025-05-15T10:00:00",
      "end_time": "2025-05-15T11:30:00",
      "duration": 90,
      "status": "upcoming",
      "total_marks": 80,
      "pass_percentage": 50,
      "qualifyingMark": null,
      "totalQuestions": 30,
      "is_published": true,
      "is_expired": false,
      "show_results_immediately": false,
      "shuffle_questions": false,
      "shuffle_options": false,
      "created_at": "2025-04-22T11:00:00"
    }
  ]
}